smic/__init__.py
smic/smic.py
smic-1.0.1.dist-info/DESCRIPTION.rst
smic-1.0.1.dist-info/METADATA
smic-1.0.1.dist-info/RECORD
smic-1.0.1.dist-info/WHEEL
smic-1.0.1.dist-info/metadata.json
smic-1.0.1.dist-info/top_level.txt
