Metadata-Version: 2.0
Name: smic
Version: 1.0.1
Summary: Image Classification library built on top of Keras. Identifies the best set of hyperparameters and trains a classification model accordingly, hence, smart.
Home-page: https://github.com/anuragmishracse/smart_image_classifier
Author: Anurag Mishra
Author-email: anuragmishracse@gmail.com
License: MIT
Keywords: image-classification deep-learning keras
Platform: UNKNOWN
Classifier: Development Status :: 3 - Alpha
Classifier: Intended Audience :: Developers
Classifier: Topic :: Software Development :: Build Tools
Classifier: License :: OSI Approved :: MIT License
Classifier: Programming Language :: Python :: 2
Classifier: Programming Language :: Python :: 2.7
Classifier: Programming Language :: Python :: 3
Classifier: Programming Language :: Python :: 3.3
Classifier: Programming Language :: Python :: 3.4
Classifier: Programming Language :: Python :: 3.5
Requires-Dist: h5py
Requires-Dist: keras
Requires-Dist: numpy
Requires-Dist: opencv-python
Requires-Dist: pandas
Requires-Dist: tensorflow
Requires-Dist: tqdm
